{
  "content": [
    {
      "content": null,
      "created": "2023-02-15T06:00:28.240769Z",
      "format": null,
      "last_modified": "2023-02-15T06:00:23.708716Z",
      "mimetype": "text/x-python",
      "name": "test_cli.py",
      "path": "importnb/docs/test_cli.py",
      "size": 2479,
      "type": "file",
      "writable": true
    },
    {
      "content": null,
      "created": "2023-02-15T06:00:28.236769Z",
      "format": null,
      "last_modified": "2023-02-15T06:00:23.704716Z",
      "mimetype": null,
      "name": "Untitled42.ipynb",
      "path": "importnb/docs/Untitled42.ipynb",
      "size": 15710,
      "type": "notebook",
      "writable": true
    },
    {
      "content": null,
      "created": "2023-02-15T06:00:28.236769Z",
      "format": null,
      "last_modified": "2023-02-15T06:00:23.704716Z",
      "mimetype": null,
      "name": "ascript.ipy",
      "path": "importnb/docs/ascript.ipy",
      "size": 25,
      "type": "file",
      "writable": true
    },
    {
      "content": null,
      "created": "2023-02-15T06:00:28.236769Z",
      "format": null,
      "last_modified": "2023-02-15T06:00:23.708716Z",
      "mimetype": "image/png",
      "name": "classes_importnb.png",
      "path": "importnb/docs/classes_importnb.png",
      "size": 191946,
      "type": "file",
      "writable": true
    },
    {
      "content": null,
      "created": "2023-02-15T06:00:28.240769Z",
      "format": null,
      "last_modified": "2023-02-15T06:00:23.708716Z",
      "mimetype": "text/x-python",
      "name": "test_importnb.py",
      "path": "importnb/docs/test_importnb.py",
      "size": 8165,
      "type": "file",
      "writable": true
    },
    {
      "content": null,
      "created": "2023-02-15T06:00:28.236769Z",
      "format": null,
      "last_modified": "2023-02-15T06:00:23.704716Z",
      "mimetype": "text/markdown",
      "name": "README.md",
      "path": "importnb/docs/README.md",
      "size": 18,
      "type": "file",
      "writable": true
    },
    {
      "content": null,
      "created": "2023-02-15T06:00:28.236769Z",
      "format": null,
      "last_modified": "2023-02-15T06:00:23.704716Z",
      "mimetype": null,
      "name": "async-cells.ipynb",
      "path": "importnb/docs/async-cells.ipynb",
      "size": 1711,
      "type": "notebook",
      "writable": true
    },
    {
      "content": null,
      "created": "2023-02-15T06:00:28.240769Z",
      "format": null,
      "last_modified": "2023-02-15T06:00:23.708716Z",
      "mimetype": null,
      "name": "test_in_notebook.ipynb",
      "path": "importnb/docs/test_in_notebook.ipynb",
      "size": 478,
      "type": "notebook",
      "writable": true
    },
    {
      "content": null,
      "created": "2023-02-15T06:00:28.240769Z",
      "format": null,
      "last_modified": "2023-02-15T06:00:23.708716Z",
      "mimetype": "image/png",
      "name": "packages_importnb.png",
      "path": "importnb/docs/packages_importnb.png",
      "size": 114698,
      "type": "file",
      "writable": true
    }
  ],
  "created": "2023-02-15T06:00:28.240769Z",
  "format": "json",
  "last_modified": "2023-02-15T06:00:28.240769Z",
  "mimetype": null,
  "name": "docs",
  "path": "importnb/docs",
  "size": null,
  "type": "directory",
  "writable": true
}