{
  "importnb": {
    "releases": {
      "6.6.6": [
        {
          "comment_text": "",
          "digests": {
            "md5": "f27a3ae7973e17d8f5eda7863f78778e",
            "sha256": "fa8d4e943f30c21032060bf92b26a099a7b9d6957e26cd386b85cdf50d88b8cf"
          },
          "downloads": -1,
          "filename": "importnb-6.6.6-py3-none-any.whl",
          "has_sig": false,
          "md5_digest": "f27a3ae7973e17d8f5eda7863f78778e",
          "packagetype": "bdist_wheel",
          "python_version": "py3",
          "requires_python": ">=3.8",
          "size": 52003,
          "upload_time": "2023-12-12T18:49:30.391176Z",
          "upload_time_iso_8601": "2023-12-12T18:49:30.391176Z",
          "url": "./importnb-6.6.6-py3-none-any.whl",
          "yanked": false,
          "yanked_reason": null
        }
      ]
    }
  },
  "midgy": {
    "releases": {
      "6.6.6": [
        {
          "comment_text": "",
          "digests": {
            "md5": "146eb026fc2735bb940d92d175c11aae",
            "sha256": "74575e4ef5830058b8ed1d6beb0329fce42bbe5c0d35ada258a2997870f1f4f6"
          },
          "downloads": -1,
          "filename": "midgy-6.6.6-py3-none-any.whl",
          "has_sig": false,
          "md5_digest": "146eb026fc2735bb940d92d175c11aae",
          "packagetype": "bdist_wheel",
          "python_version": "py3",
          "requires_python": ">=3.7",
          "size": 13491,
          "upload_time": "2023-12-12T18:49:22.431239Z",
          "upload_time_iso_8601": "2023-12-12T18:49:22.431239Z",
          "url": "./midgy-6.6.6-py3-none-any.whl",
          "yanked": false,
          "yanked_reason": null
        }
      ]
    }
  },
  "pidgy": {
    "releases": {
      "6.6.6": [
        {
          "comment_text": "",
          "digests": {
            "md5": "444a6501f6003c65dffe07af4487b130",
            "sha256": "f687c87a9541a3d26723361621771d36883456cc49962afe5bfc017129b32928"
          },
          "downloads": -1,
          "filename": "pidgy-6.6.6-py3-none-any.whl",
          "has_sig": false,
          "md5_digest": "444a6501f6003c65dffe07af4487b130",
          "packagetype": "bdist_wheel",
          "python_version": "py3",
          "requires_python": ">=3.7",
          "size": 30185,
          "upload_time": "2023-12-12T18:49:26.027212Z",
          "upload_time_iso_8601": "2023-12-12T18:49:26.027212Z",
          "url": "./pidgy-6.6.6-py3-none-any.whl",
          "yanked": false,
          "yanked_reason": null
        }
      ]
    }
  }
}